pysampletoolkit.cpython-311-x86_64-linux-gnu.so
pyluban.cpython-311-x86_64-linux-gnu.so
pysampletoolkit-1.0.8.dist-info/WHEEL
pysampletoolkit-1.0.8.dist-info/METADATA
pysampletoolkit-1.0.8.dist-info/top_level.txt
pysampletoolkit-1.0.8.dist-info/LICENSE
pysampletoolkit-1.0.8.dist-info/RECORD
